cascade/__init__.py
cascade/api.py
cascade/core/__init__.py
cascade/core/coercion.py
cascade/core/errors.py
cascade/core/registry.py
cascade/core/types.py
cascade/dataclass/__init__.py
cascade/dataclass/field.py
cascade/dataclass/validated.py
cascade/profiles/__init__.py
cascade/profiles/context.py
cascade/profiles/manager.py
cascade/rules/__init__.py
cascade/rules/base.py
cascade/rules/common.py
cascade_framework-1.0.1.dist-info/licenses/LICENSE
cascade_framework-1.0.1.dist-info/METADATA
cascade_framework-1.0.1.dist-info/WHEEL
cascade_framework-1.0.1.dist-info/top_level.txt
cascade_framework-1.0.1.dist-info/RECORD
