Metadata-Version: 2.4
Name: cascade-framework
Version: 1.0.1
Summary: Explicit, deterministic runtime validation framework for Python
Author: XGCascade
Author-email: XGCascade <cascade.framework@proton.me>
License: MIT License
Classifier: Development Status :: 5 - Production/Stable
Classifier: Intended Audience :: Developers
Classifier: License :: OSI Approved :: MIT License
Classifier: Programming Language :: Python :: 3
Classifier: Programming Language :: Python :: 3 :: Only
Classifier: Programming Language :: Python :: 3.10
Classifier: Programming Language :: Python :: 3.11
Classifier: Programming Language :: Python :: 3.12
Classifier: Typing :: Typed
Requires-Python: >=3.10
License-File: LICENSE
Dynamic: author
Dynamic: license-file
Dynamic: requires-python
